Workbook
Name SelCounty: OFFSET('[1]County Populations'!$C$2,'[1]County Populations'!$M$6-1,0,'[1]County Populations'!$M$7-'[1]County Populations'!$M$6+1,1)

Sheet County Summary
B2: County (Population) - Threshold | D2: FEMA Inspector | E2: Emergency Work | G2: Permanent Work | L2: Total
B3: Grand Traverse County (95,238) - $462,856.68 | D3: Connor Blevins | E3: =SUM(Table6[[A]:[B]]) -> 341429.52 | G3: =SUM(Table6[[C]:[G]]) -> 2348901.5 | L3: =SUM(Table6[Applicant Total]) -> 2690331
B5: Applicant | C5: Type | D5: Status | E5: A | F5: B | G5: C | H5: D | I5: E | J5: F | K5: G | L5: Applicant Total
B6: Garfield Township | C6: Government | D6: Complete | I6: 73925.12 | K6: 60346.27 | L6: =SUM(Table6[[#This Row],[A]:[G]]) -> 134271.39
B7: Traverse City | C7: City | D7: Complete | E7: 0 | F7: 0 | G7: 35750 | K7: 294071 | L7: =SUM(Table6[[#This Row],[A]:[G]]) -> 329821
B8: Grand Traverse County Roads | C8: County | D8: Complete | E8: 198000 | F8: 138929.52 | G8: 1657333.5 | L8: =SUM(Table6[[#This Row],[A]:[G]]) -> 1994263
B9: Grand Traverse County Parks | C9: County | D9: Complete | F9: 4500 | K9: 226075.57 | L9: =SUM(Table6[[#This Row],[A]:[G]]) -> 230575.57
B10: MDNR - Grand Traverse County | C10: Government | D10: Complete | K10: 1400 | L10: =SUM(Table6[[#This Row],[A]:[G]]) -> 1400
L11: =SUM(Table6[[#This Row],[A]:[G]]) -> 0
L12: =SUM(Table6[[#This Row],[A]:[G]]) -> 0
L13: =SUM(Table6[[#This Row],[A]:[G]]) -> 0
L14: =SUM(Table6[[#This Row],[A]:[G]]) -> 0
L15: =SUM(Table6[[#This Row],[A]:[G]]) -> 0
L16: =SUM(Table6[[#This Row],[A]:[G]]) -> 0
L17: =SUM(Table6[[#This Row],[A]:[G]]) -> 0
L18: =SUM(Table6[[#This Row],[A]:[G]]) -> 0
L19: =SUM(Table6[[#This Row],[A]:[G]]) -> 0
L20: =SUM(Table6[[#This Row],[A]:[G]]) -> 0
L21: =SUM(Table6[[#This Row],[A]:[G]]) -> 0
L22: =SUM(Table6[[#This Row],[A]:[G]]) -> 0
... L101: =SUM(Table6[[#This Row],[A]:[G]]) -> 0

Sheet Reductions
B2: Applicant | C2: Category | D2: Original Costs | E2: Eligible Costs | F2: Reduction | G2: Reduction Category | H2: Notes
F3: =SUM(Table4[[#This Row],[Eligible Costs]]-Table4[[#This Row],[Original Costs]]) -> 0
F4: =SUM(Table4[[#This Row],[Eligible Costs]]-Table4[[#This Row],[Original Costs]]) -> 0
F5: =SUM(Table4[[#This Row],[Eligible Costs]]-Table4[[#This Row],[Original Costs]]) -> 0
F6: =SUM(Table4[[#This Row],[Eligible Costs]]-Table4[[#This Row],[Original Costs]]) -> 0
F7: =SUM(Table4[[#This Row],[Eligible Costs]]-Table4[[#This Row],[Original Costs]]) -> 0
F8: =SUM(Table4[[#This Row],[Eligible Costs]]-Table4[[#This Row],[Original Costs]]) -> 0
F9: =SUM(Table4[[#This Row],[Eligible Costs]]-Table4[[#This Row],[Original Costs]]) -> 0
F10: =SUM(Table4[[#This Row],[Eligible Costs]]-Table4[[#This Row],[Original Costs]]) -> 0
F11: =SUM(Table4[[#This Row],[Eligible Costs]]-Table4[[#This Row],[Original Costs]]) -> 0
F12: =SUM(Table4[[#This Row],[Eligible Costs]]-Table4[[#This Row],[Original Costs]]) -> 0
F13: =SUM(Table4[[#This Row],[Eligible Costs]]-Table4[[#This Row],[Original Costs]]) -> 0
F14: =SUM(Table4[[#This Row],[Eligible Costs]]-Table4[[#This Row],[Original Costs]]) -> 0
... F100: =SUM(Table4[[#This Row],[Eligible Costs]]-Table4[[#This Row],[Original Costs]]) -> 0

Sheet Comments
A1: Applicant | B1: Comments
A2: ='County Summary'!B6 -> Garfield Township | B2: Cat E: Estimated: $184,312.80 ($175,967.80 and $8,345 contracts) to clean, sanitize, and remove indoor flooring at the YMCA South location. Validated with photos, invoices, and insurance denial letter. Validated: $73,925.12 Reduced: $110,387.68 because located in a floodplain for estimated NFIP proceeds Applicant would have received had been covered coverage. See attached spreadsheet for calculations. Applicant indicates lease agreement does not put costs onto lesee entity. Cat G: Estimated: $60,346.27 Validated: $60,346.27 Reduced: $0 - TC Commons Garfield Trail: FEMA eng. estimated 200 FT x 3 FT x 2 FT deep trail (45 CY x 60.33 per CY = $2,715) washout repair based on photos. - Boardman River Trail, provided lump sum of $50,000 for mud on trails, 2 displaced bridges. Validated reasonable sum based on photos/GPS coordinates. - Staff costs to clean flooded pickleball court: $7,631.27 Note: Initial spreadsheet included $65,000 several items that ended up not being damaged by the incident or will fall under Grand Traverse Parks. Note: Trail/Pickleball restoration will likely include both Cat A and B work, not split out.
A3: ='County Summary'!B7 -> Traverse City | B3: Cat A: Estimated: $2,066.02 for tree removal, removal of debris from creeks. Reduced: $2,066.02 for being below the FY 26 minimum project threshold Cat B: Estimated: $1,385.72 for barricading, sandbagging, temporary emergency repairs, emergency response activities. Reduced $1,385.72 for being below the FR 26 minimum project threshold. Cat C: Estimated: $35,750 for damaged sidewalk underneath N Union St. Bridge. Validated: $35,750 using applicant provided pictures, invoices, and documents. Cat G: Estimated: $294,071 for a destroyed wooden footpath bridge, sink hole in parking lot, replacement of destroyed sidewalk in parking lot sink hole, and erosions of parking lot. Validated: $294,071 using applicant provided pictures, invoices, and documents. -Site 1 Estimated: $135,108, Grasshopper pedestrian bridge. Validated: $135,108 using applicant provided pictures and invoices -Site 2 Estimated: $96,463 Lot A sidewalk that fell into the adjacent stream after a sinkhole formed underneath the pavement. Validated: $96,463 using applicant provided pictures and invoices, cost updated to include additional replacement of lost sidewalk that was not included in initial estimates. -Site 3 Estimated: $62,500 Lot K, erosion of embankment and retaining wall adjacent to a parking lot by the stream, the erosion resulted in a loss of retaining wall and fill material. Validated: $62,500 using applicant provided invoices and pictures
A4: ='County Summary'!B8 -> Grand Traverse County Roads | B4: Cat A: Estimated $198,000 for debris removal on roads at 13 sites. Validated: $198,000, pending RFI for additional $21,000. Potential to add less than $100,000 from 1 more site. Cat B: Estimated: $0 initially. Validated: $138,929.52 with contract invoices for emergency pumping, barricades and traffic control for FHWA roads and other facilities. Cat C: Estimated: $12,738,000 for WC/WTBC road repairs at 173 sites. Validated: $1,657,333.52 with a sampling of cost estimates, provided invoices, F/A Labor/Equipment Summaries, and photos showing damage with reasonable lump sums. Reduced: $11,080,666.48 for repairs to FHWA roads and clarifying certain estimated costs were not in-kind. See "Grand Traverse Roads Commission Validation Sheet" for detailed information by WO. Top-line notes: - Reduced $6,771,899.98 for 35 repair sites located on federal-aid roads - Reduced $3,855,628.50 on Brown Bridge Rd originally estimated full replacement including upgrade to spanned bridge ($4m), actual repair involves unearthing and repacking two large culverts, not bridge replacement. Applicant provided a contract quote for repairs and emergency repairs totaling $144,371.50. - Reduced $381,000 for other estimated repairs which are not in-kind (e.g., adding new culverts, upsizing culverts) at 9 sites - Reduced $72,138 after Applicant clarified SOW and provided in-kind costs for 2 sites - some of these costs were captured in the EPMs. - For approx 78 sites, FEMA validated either with photos with reasonable lump sum linked work orders, site visits, or cost documentation. Validated remaining 73 sites where photos were not provided or unclear which photos due to large sample. (approx. $538,000)
A5: ='County Summary'!B9 -> Grand Traverse County Parks | B5: Cat A: Estimated: $0, for debris removal contract labor from park facilities and pathways. Validated: $4,500 using applicant provided invoices and activity descriptions Cat G: Estimated: $2,255,000 for washed out trail restoration at several sites, replacement of a pedestrian bridge, repairs to a service road, and replacement of a scenic overlook. See more details at "Grand Traverse Extra Notes." Reduced: $2,028,924.43 - unable to validate most lump sums based on site visits or provided documentation. Revised $13m cost estimate did not tie to the observed damage. Validated: $226,075.57 using applicant provided estimate and pictures. - Oleson Bridge: Estimated: $800,000 to replace a footbridge. Reduced: $797,500 Photos show a tree that fell on one end of the bridge and limited washout around one abutment. Validated: $2,500 using FEMA engineer estimate for the removal of a tree and the repair/stabilization of the bridge abutment. - Beaver Pond Trail: Estimated: $175,000, lump sum estimate provided. Reduced: $169,356.82 Validated $5,643.18 based on FEMA estimate of damaged dimensions to the trail. - BRT service road: Estimated: $80,000 BRT service road washed out by the flood. Validated: $80,000 using applicant provided pictures and cost estimate - Oleson trail washout: Estimated $500,000 with lump sum cost. Reduced: $ because unable to tie cost to work to restore the trail to pre-disaster conditions. Validated: $12,124.27 with FEMA eng. cost estimate to repair the trail. - Keystone Overlook: Estimated: $200,000.00 lump sum. Validated: $105,883.22 based on FEMA engineer estimate. Reduced. $94,116.78 - unable to tie lump sum to lump sum. - Keystone Rapids Trail: Estimated: $500,000 with lump sum cost. Reduced: $180,075.10 due to lump sums provided not tied to trail restoration. Validated: $19,924.90 with FEMA engineer estimate to restore to predisaster conditions.
A6: ='County Summary'!B10 -> MDNR - Grand Traverse County | B6: Cat G: Estimated: $1,400 for repairs to parking lot, bathrooms, and roadways/access site. Validated: $1,400 using applicant provided cost estimates
A7: ='County Summary'!B11 -> 0
A8: ='County Summary'!B12 -> 0
A9: ='County Summary'!B13 -> 0
A10: ='County Summary'!B14 -> 0
A11: ='County Summary'!B15 -> 0
A12: ='County Summary'!B16 -> 0
A13: ='County Summary'!B17 -> 0
A14: ='County Summary'!B18 -> 0
A15: ='County Summary'!B19 -> 0
A16: ='County Summary'!B20 -> 0
A17: ='County Summary'!B21 -> 0
A18: ='County Summary'!B22 -> 0
... A100: ='County Summary'!B104 -> 0

Sheet Notes
A1: Created by Charles Annerino
A2: Charles.Annerino@fema.dhs.gov

Sheet County Population and Threshold
A1: Michigan (10,077,331) - $19,550,022
A3: County (Population) - Threshold | C3: Team Leads
A4: =D4 & " (" &F4& ")" & " - " &H4 -> Alcona County (10,167) - $49,411.62 | C4: Anessa Jones | D4: Alcona County | E4: 10167 | F4: 10,167 | G4: =E4*4.86 -> 49411.62 | H4: =TEXT(G4,"$#,##0.00") -> $49,411.62
A5: =D5 & " (" &F5& ")" & " - " &H5 -> Alger County (8,842) - $42,972.12 | C5: Angela Williams | D5: Alger County | E5: 8842 | F5: 8,842 | G5: =E5*4.86 -> 42972.12 | H5: =TEXT(G5,"$#,##0.00") -> $42,972.12
A6: =D6 & " (" &F6& ")" & " - " &H6 -> Allegan County (120,502) - $585,639.72 | C6: Bassam Efein | D6: Allegan County | E6: 120502 | F6: 120,502 | G6: =E6*4.86 -> 585639.72 | H6: =TEXT(G6,"$#,##0.00") -> $585,639.72
A7: =D7 & " (" &F7& ")" & " - " &H7 -> Alpena County (28,907) - $140,488.02 | C7: Caleb Smith | D7: Alpena County | E7: 28907 | F7: 28,907 | G7: =E7*4.86 -> 140488.02 | H7: =TEXT(G7,"$#,##0.00") -> $140,488.02
A8: =D8 & " (" &F8& ")" & " - " &H8 -> Antrim County (23,431) - $113,874.66 | C8: Catherine Waren | D8: Antrim County | E8: 23431 | F8: 23,431 | G8: =E8*4.86 -> 113874.66 | H8: =TEXT(G8,"$#,##0.00") -> $113,874.66
A9: =D9 & " (" &F9& ")" & " - " &H9 -> Arenac County (15,002) - $72,909.72 | C9: Connor Blevins | D9: Arenac County | E9: 15002 | F9: 15,002 | G9: =E9*4.86 -> 72909.72 | H9: =TEXT(G9,"$#,##0.00") -> $72,909.72
A10: =D10 & " (" &F10& ")" & " - " &H10 -> Baraga County (8,158) - $39,647.88 | C10: Eric Punzalan | D10: Baraga County | E10: 8158 | F10: 8,158 | G10: =E10*4.86 -> 39647.88 | H10: =TEXT(G10,"$#,##0.00") -> $39,647.88
A11: =D11 & " (" &F11& ")" & " - " &H11 -> Barry County (62,423) - $303,375.78 | C11: Javon Cotton | D11: Barry County | E11: 62423 | F11: 62,423 | G11: =E11*4.86 -> 303375.78 | H11: =TEXT(G11,"$#,##0.00") -> $303,375.78
A12: =D12 & " (" &F12& ")" & " - " &H12 -> Bay County (103,856) - $504,740.16 | C12: Jennifer Grobe | D12: Bay County | E12: 103856 | F12: 103,856 | G12: =E12*4.86 -> 504740.16 | H12: =TEXT(G12,"$#,##0.00") -> $504,740.16
A13: =D13 & " (" &F13& ")" & " - " &H13 -> Benzie County (17,970) - $87,334.20 | C13: Richard Chiarello | D13: Benzie County | E13: 17970 | F13: 17,970 | G13: =E13*4.86 -> 87334.2 | H13: =TEXT(G13,"$#,##0.00") -> $87,334.20
A14: =D14 & " (" &F14& ")" & " - " &H14 -> Berrien County (154,316) - $749,975.76 | C14: Roopak Hanna | D14: Berrien County | E14: 154316 | F14: 154,316 | G14: =E14*4.86 -> 749975.76 | H14: =TEXT(G14,"$#,##0.00") -> $749,975.76
A15: =D15 & " (" &F15& ")" & " - " &H15 -> Branch County (44,862) - $218,029.32 | C15: Shawana Thomas | D15: Branch County | E15: 44862 | F15: 44,862 | G15: =E15*4.86 -> 218029.32 | H15: =TEXT(G15,"$#,##0.00") -> $218,029.32
A16: =D16 & " (" &F16& ")" & " - " &H16 -> Calhoun County (134,310) - $652,746.60 | C16: Tracie Smith | D16: Calhoun County | E16: 134310 | F16: 134,310 | G16: =E16*4.86 -> 652746.6 | H16: =TEXT(G16,"$#,##0.00") -> $652,746.60
A17: =D17 & " (" &F17& ")" & " - " &H17 -> Cass County (51,589) - $250,722.54 | D17: Cass County | E17: 51589 | F17: 51,589 | G17: =E17*4.86 -> 250722.54 | H17: =TEXT(G17,"$#,##0.00") -> $250,722.54
A18: =D18 & " (" &F18& ")" & " - " &H18 -> Charlevoix County (26,054) - $126,622.44 | D18: Charlevoix County | E18: 26054 | F18: 26,054 | G18: =E18*4.86 -> 126622.44 | H18: =TEXT(G18,"$#,##0.00") -> $126,622.44
A19: =D19 & " (" &F19& ")" & " - " &H19 -> Cheboygan County (25,579) - $124,313.94 | D19: Cheboygan County | E19: 25579 | F19: 25,579 | G19: =E19*4.86 -> 124313.94 | H19: =TEXT(G19,"$#,##0.00") -> $124,313.94
A20: =D20 & " (" &F20& ")" & " - " &H20 -> Chippewa County (36,785) - $178,775.10 | D20: Chippewa County | E20: 36785 | F20: 36,785 | G20: =E20*4.86 -> 178775.1 | H20: =TEXT(G20,"$#,##0.00") -> $178,775.10
A21: =D21 & " (" &F21& ")" & " - " &H21 -> Clare County (30,856) - $149,960.16 | D21: Clare County | E21: 30856 | F21: 30,856 | G21: =E21*4.86 -> 149960.16 | H21: =TEXT(G21,"$#,##0.00") -> $149,960.16
A22: =D22 & " (" &F22& ")" & " - " &H22 -> Clinton County (79,128) - $384,562.08 | D22: Clinton County | E22: 79128 | F22: 79,128 | G22: =E22*4.86 -> 384562.08 | H22: =TEXT(G22,"$#,##0.00") -> $384,562.08
A23: =D23 & " (" &F23& ")" & " - " &H23 -> Crawford County (12,988) - $63,121.68 | D23: Crawford County | E23: 12988 | F23: 12,988 | G23: =E23*4.86 -> 63121.68 | H23: =TEXT(G23,"$#,##0.00") -> $63,121.68
A24: =D24 & " (" &F24& ")" & " - " &H24 -> Delta County (36,903) - $179,348.58 | D24: Delta County | E24: 36903 | F24: 36,903 | G24: =E24*4.86 -> 179348.58 | H24: =TEXT(G24,"$#,##0.00") -> $179,348.58
A25: =D25 & " (" &F25& ")" & " - " &H25 -> Dickinson County (25,947) - $126,102.42 | D25: Dickinson County | E25: 25947 | F25: 25,947 | G25: =E25*4.86 -> 126102.42 | H25: =TEXT(G25,"$#,##0.00") -> $126,102.42
A26: =D26 & " (" &F26& ")" & " - " &H26 -> Eaton County (109,175) - $530,590.50 | D26: Eaton County | E26: 109175 | F26: 109,175 | G26: =E26*4.86 -> 530590.5 | H26: =TEXT(G26,"$#,##0.00") -> $530,590.50
A27: =D27 & " (" &F27& ")" & " - " &H27 -> Emmet County (34,112) - $165,784.32 | D27: Emmet County | E27: 34112 | F27: 34,112 | G27: =E27*4.86 -> 165784.32 | H27: =TEXT(G27,"$#,##0.00") -> $165,784.32
A28: =D28 & " (" &F28& ")" & " - " &H28 -> Genesee County (406,211) - $1,974,185.46 | D28: Genesee County | E28: 406211 | F28: 406,211 | G28: =E28*4.86 -> 1974185.5 | H28: =TEXT(G28,"$#,##0.00") -> $1,974,185.46
... A86: =D86 & " (" &F86& ")" & " - " &H86 -> Wexford County (33,673) - $163,650.78 | D86: Wexford County | E86: 33673 | F86: 33,673 | G86: =E86*4.86 -> 163650.78 | H86: =TEXT(G86,"$#,##0.00") -> $163,650.78
